{
  "lastUpdated": "2026-02-18T19:33:27.648Z",
  "overall": "up",
  "services": [
    {
      "name": "API",
      "url": "https://api.vaultbrix.com/health",
      "status": "up",
      "code": 200,
      "responseTime": 532,
      "uptime": 96.98,
      "avgResponseTime": 731
    },
    {
      "name": "Dashboard",
      "url": "https://app.vaultbrix.com",
      "status": "up",
      "code": 307,
      "responseTime": 483,
      "uptime": 100,
      "avgResponseTime": 722
    },
    {
      "name": "Website",
      "url": "https://vaultbrix.com",
      "status": "up",
      "code": 200,
      "responseTime": 579,
      "uptime": 97.49,
      "avgResponseTime": 650
    },
    {
      "name": "Auth Service",
      "url": "https://api.vaultbrix.com/v1/auth/health",
      "status": "up",
      "code": 401,
      "responseTime": 465,
      "uptime": 100,
      "avgResponseTime": 586
    }
  ]
}