{
  "lastUpdated": "2026-02-18T06:43:07.618Z",
  "overall": "up",
  "services": [
    {
      "name": "API",
      "url": "https://api.vaultbrix.com/health",
      "status": "up",
      "code": 200,
      "responseTime": 575,
      "uptime": 96.77,
      "avgResponseTime": 728
    },
    {
      "name": "Dashboard",
      "url": "https://app.vaultbrix.com",
      "status": "up",
      "code": 307,
      "responseTime": 490,
      "uptime": 100,
      "avgResponseTime": 726
    },
    {
      "name": "Website",
      "url": "https://vaultbrix.com",
      "status": "up",
      "code": 200,
      "responseTime": 553,
      "uptime": 97.31,
      "avgResponseTime": 649
    },
    {
      "name": "Auth Service",
      "url": "https://api.vaultbrix.com/v1/auth/health",
      "status": "up",
      "code": 401,
      "responseTime": 413,
      "uptime": 100,
      "avgResponseTime": 588
    }
  ]
}