{
  "lastUpdated": "2026-04-22T10:32:15.955Z",
  "overall": "degraded",
  "services": [
    {
      "name": "API",
      "url": "https://api.vaultbrix.com/health",
      "status": "up",
      "code": 200,
      "responseTime": 728,
      "uptime": 99.77,
      "avgResponseTime": 687
    },
    {
      "name": "Dashboard",
      "url": "https://app.vaultbrix.com",
      "status": "up",
      "code": 307,
      "responseTime": 722,
      "uptime": 99.83,
      "avgResponseTime": 669
    },
    {
      "name": "Website",
      "url": "https://vaultbrix.com",
      "status": "down",
      "code": 0,
      "responseTime": 428,
      "uptime": 99.56,
      "avgResponseTime": 627
    },
    {
      "name": "Auth Service",
      "url": "https://api.vaultbrix.com/v1/auth/health",
      "status": "up",
      "code": 401,
      "responseTime": 713,
      "uptime": 99.83,
      "avgResponseTime": 577
    }
  ]
}