{
  "lastUpdated": "2026-03-13T06:57:32.302Z",
  "overall": "up",
  "services": [
    {
      "name": "API",
      "url": "https://api.vaultbrix.com/health",
      "status": "up",
      "code": 200,
      "responseTime": 670,
      "uptime": 99.38,
      "avgResponseTime": 712
    },
    {
      "name": "Dashboard",
      "url": "https://app.vaultbrix.com",
      "status": "up",
      "code": 307,
      "responseTime": 510,
      "uptime": 99.79,
      "avgResponseTime": 687
    },
    {
      "name": "Website",
      "url": "https://vaultbrix.com",
      "status": "up",
      "code": 301,
      "responseTime": 578,
      "uptime": 99.38,
      "avgResponseTime": 639
    },
    {
      "name": "Auth Service",
      "url": "https://api.vaultbrix.com/v1/auth/health",
      "status": "up",
      "code": 401,
      "responseTime": 4662,
      "uptime": 99.9,
      "avgResponseTime": 577
    }
  ]
}